typhe/__init__.py
typhe/main.py
typhe-2025.0.0.dist-info/licenses/LICENSE
typhe-2025.0.0.dist-info/METADATA
typhe-2025.0.0.dist-info/WHEEL
typhe-2025.0.0.dist-info/top_level.txt
typhe-2025.0.0.dist-info/RECORD
