Metadata-Version: 2.4
Name: typhe
Version: 2025.0.0
Summary: More types for Python.
Author-email: ItsKayraa <kayrabalc399@gmail.com>
License: GPL3
Project-URL: Homepage, https://github.com/ItsKayraa/typhe
Project-URL: Bug Tracker, https://github.com/ItsKayraa/typhe/issues
Requires-Python: >=3.8
License-File: LICENSE
Dynamic: license-file
